ytbrf/__init__.py
ytbrf/config.py
ytbrf/test_youtube.py
ytbrf/youtube.py
ytbrf-0.1.1.dist-info/METADATA
ytbrf-0.1.1.dist-info/WHEEL
ytbrf-0.1.1.dist-info/entry_points.txt
ytbrf-0.1.1.dist-info/top_level.txt
ytbrf-0.1.1.dist-info/RECORD
