Metadata-Version: 2.4
Name: ytbrf
Version: 0.1.1
Summary: A CLI tool to transcribe, summarize and translate YouTube videos
Home-page: 
Author: allenlsy
Author-email: allenlsy@gmail.com
Classifier: Programming Language :: Python :: 3
Classifier: License :: OSI Approved :: MIT License
Classifier: Operating System :: OS Independent
Requires-Python: >=3.8
Requires-Dist: yt-dlp>=2023.12.30
Requires-Dist: typer>=0.9.0
Requires-Dist: rich>=13.7.0
Requires-Dist: google-api-python-client>=2.108.0
Requires-Dist: google-auth-oauthlib>=1.1.0
Requires-Dist: transformers>=4.36.0
Requires-Dist: torch>=2.1.0
Requires-Dist: sentencepiece>=0.1.99
Requires-Dist: protobuf>=4.25.1
Dynamic: author
Dynamic: author-email
Dynamic: classifier
Dynamic: description
Dynamic: description-content-type
Dynamic: requires-dist
Dynamic: requires-python
Dynamic: summary
